xiaokonglong/__init__.py
xiaokonglong/read.py
xiaokonglong/write.py
xiaokonglong-0.1.1.dist-info/METADATA
xiaokonglong-0.1.1.dist-info/WHEEL
xiaokonglong-0.1.1.dist-info/top_level.txt
xiaokonglong-0.1.1.dist-info/RECORD
